Metadata-Version: 2.4
Name: iflow-mcp_searchapi-mcp
Version: 1.0.0
Summary: A Model Context Protocol server for SearchAPI.io services including Google Search, Maps, Flights, Hotels and more
Author-email: iflow-mcp <iflow-mcp@example.com>
License: MIT
Project-URL: Homepage, https://github.com/iflow-mcp/searchapi-mcp
Project-URL: Repository, https://github.com/iflow-mcp/searchapi-mcp
Project-URL: Issues, https://github.com/iflow-mcp/searchapi-mcp/issues
Classifier: Development Status :: 4 - Beta
Classifier: Intended Audience :: Developers
Classifier: License :: OSI Approved :: MIT License
Classifier: Programming Language :: Python :: 3
Classifier: Programming Language :: Python :: 3.7
Classifier: Programming Language :: Python :: 3.8
Classifier: Programming Language :: Python :: 3.9
Classifier: Programming Language :: Python :: 3.10
Classifier: Programming Language :: Python :: 3.11
Classifier: Programming Language :: Python :: 3.12
Requires-Python: >=3.7
License-File: LICENSE
Requires-Dist: httpx>=0.24.0
Requires-Dist: fastmcp>=0.1.0
Requires-Dist: python-dotenv>=1.0.0
Dynamic: license-file
